countrycodesbbb/__init__.py
countrycodesbbb-0.0.3.dist-info/METADATA
countrycodesbbb-0.0.3.dist-info/WHEEL
countrycodesbbb-0.0.3.dist-info/top_level.txt
countrycodesbbb-0.0.3.dist-info/RECORD
