Metadata-Version: 2.1
Name: countrycodesbbb
Version: 0.0.3
Summary: A basic package for helping Sloths team with country codes
Home-page: UNKNOWN
Author: VS
Author-email: email.com@gmail.com
License: UNKNOWN
Keywords: python,Sloths,360,country codes
Platform: UNKNOWN
Classifier: Development Status :: 1 - Planning
Classifier: Intended Audience :: Developers
Classifier: Programming Language :: Python :: 3
Classifier: Operating System :: Unix
Classifier: Operating System :: MacOS :: MacOS X
Classifier: Operating System :: Microsoft :: Windows
